netbox_hidebox/__init__.py
netbox_hidebox/middleware.py
netbox_hidebox/signals.py
netbox_hidebox/version.py
netbox_hidebox-1.2.3.dist-info/licenses/LICENSE
netbox_hidebox-1.2.3.dist-info/METADATA
netbox_hidebox-1.2.3.dist-info/WHEEL
netbox_hidebox-1.2.3.dist-info/top_level.txt
netbox_hidebox-1.2.3.dist-info/RECORD
