Metadata-Version: 2.4
Name: netbox_hidebox
Version: 1.2.3
Summary: Hide Unwanted Fields Based On User-Groups
Home-page: 
Author: Sofien Aouni
Author-email: contact@sofien.meme
Maintainer: AOS
License-File: LICENSE
Dynamic: author
Dynamic: author-email
Dynamic: description
Dynamic: description-content-type
Dynamic: license-file
Dynamic: maintainer
Dynamic: summary
